pyppyn/__init__.py
pyppyn/cli.py
pyppyn/logging.conf
pyppyn-0.5.5.dist-info/LICENSE
pyppyn-0.5.5.dist-info/METADATA
pyppyn-0.5.5.dist-info/WHEEL
pyppyn-0.5.5.dist-info/entry_points.txt
pyppyn-0.5.5.dist-info/top_level.txt
pyppyn-0.5.5.dist-info/RECORD
